{
    "posts": [{
            "title": "Con tutela, buscan revivir las 16 curules para las víctimas en el Congreso",
            "description": "Este viernes radicaron una tutela en el Tribunal de Cundinamarca para que reviva la iniciativa.",
            "id": 1
        },
        {
            "title": "Esta es la ubicación de las gasolineras sancionadas por la SIC",
            "description": "Por no entregar la cantidad exacta, las estaciones multadas deben pagar 682 millones de pesos.",
            "id": 2
        }
    ],
    "comments": [{
            "id": 1,
            "body": "Este es un buen momento para hacer un comentario",
            "postId": 1
        },
        {
            "id": 2,
            "body": "El segundo comentario que hago en esta prueba",
            "postId": 2
        },
        {
            "id": 3,
            "body": "Este es el ultimo comentario",
            "postId": 1
        }
    ]
}